<?xml version="1.0" encoding="utf-8"?>
<odoo>

    <data>

        <record id="view_pos_pos_form_inherit_pos_slip_number" model="ir.ui.view">
            <field name="name">view.pos.pos.form.inherit.pos.slip.number</field>
            <field name="model">pos.order</field>
            <field name="inherit_id" ref="point_of_sale.view_pos_pos_form"/>
            <field name="arch" type="xml">
                <xpath expr="//field[@name='name']" position="after">
                    <field name="sequence_num" />
                </xpath>
            </field>
        </record>

    </data>

</odoo>
